cql/__init__.py
cql/commons_pb2.py
cql/commons_pb2_grpc.py
cql/find_command_pb2.py
cql/find_command_pb2_grpc.py
cql/get_command_pb2.py
cql/get_command_pb2_grpc.py
cql/set_command_pb2.py
cql/set_command_pb2_grpc.py
cranky/__init__.py
cranky/main.py
server/__init__.py
server/server_service_pb2.py
server/server_service_pb2_grpc.py
cranky-0.1.0b2.dist-info/LICENCE
cranky-0.1.0b2.dist-info/METADATA
cranky-0.1.0b2.dist-info/WHEEL
cranky-0.1.0b2.dist-info/top_level.txt
cranky-0.1.0b2.dist-info/RECORD
