Metadata-Version: 2.1
Name: cranky
Version: 0.1.0b2
Summary: CrankDB python database driver.
Home-page: https://github.com/shreybatra/cranky
Author: Shrey Batra
Author-email: shreybatra97@gmail.com
License: UNKNOWN
Platform: UNKNOWN
Classifier: Programming Language :: Python :: 3
Classifier: License :: OSI Approved :: MIT License
Classifier: Operating System :: OS Independent
Requires-Python: >=3.6
License-File: LICENCE
Requires-Dist: grpcio
Requires-Dist: google
Requires-Dist: protobuf
